{"97701_0001":{"part_P22":53.2,"lfi_P22":0.0,"gauche_P22":3.9,"rn_P22":21.3,"em_P22":11.8,"lr_P22":3.0,"part_E24":22.2,"lfi_E24":2.8,"gauche_E24":4.0,"rn_E24":10.7,"em_E24":3.3,"lr_E24":2.0,"dpart":41.7,"abst":855},"97701_0002":{"part_P22":51.8,"lfi_P22":0.0,"gauche_P22":4.6,"rn_P22":18.9,"em_P22":11.9,"lr_P22":4.8,"part_E24":21.9,"lfi_E24":1.6,"gauche_E24":4.5,"rn_E24":10.8,"em_E24":2.0,"lr_E24":2.4,"dpart":42.2,"abst":822},"97701_0003":{"part_P22":52.9,"lfi_P22":0.0,"gauche_P22":3.2,"rn_P22":20.8,"em_P22":13.0,"lr_P22":2.3,"part_E24":22.9,"lfi_E24":1.8,"gauche_E24":4.2,"rn_E24":11.0,"em_E24":3.4,"lr_E24":3.0,"dpart":43.3,"abst":785},"97701_0004":{"part_P22":49.0,"lfi_P22":0.0,"gauche_P22":3.7,"rn_P22":18.2,"em_P22":11.0,"lr_P22":3.4,"part_E24":18.4,"lfi_E24":2.3,"gauche_E24":4.6,"rn_E24":8.2,"em_E24":2.7,"lr_E24":1.8,"dpart":37.6,"abst":922},"97701_0005":{"part_P22":49.6,"lfi_P22":0.0,"gauche_P22":2.8,"rn_P22":21.6,"em_P22":12.1,"lr_P22":2.5,"part_E24":24.1,"lfi_E24":1.3,"gauche_E24":3.2,"rn_E24":12.7,"em_E24":3.2,"lr_E24":1.9,"dpart":48.5,"abst":740},"97701_1":{"part_L24":41.1,"lfi_L24":0.0,"gauche_L24":0.0,"rn_L24":5.5,"em_L24":9.6,"lr_L24":22.3},"97701_2":{"part_L24":40.5,"lfi_L24":0.0,"gauche_L24":0.0,"rn_L24":5.6,"em_L24":7.8,"lr_L24":24.1},"97701_3":{"part_L24":41.3,"lfi_L24":0.0,"gauche_L24":0.0,"rn_L24":4.6,"em_L24":8.9,"lr_L24":25.5},"97701_4":{"part_L24":39.9,"lfi_L24":0.0,"gauche_L24":0.0,"rn_L24":3.1,"em_L24":9.5,"lr_L24":23.3},"97701_5":{"part_L24":40.3,"lfi_L24":0.0,"gauche_L24":0.0,"rn_L24":6.1,"em_L24":8.0,"lr_L24":23.4},"97701_0006":{"dpart":NaN}}